glaium_sdk/__init__.py
glaium_sdk/agent.py
glaium_sdk/client.py
glaium_sdk/optimization.py
glaium_sdk-0.1.2.dist-info/METADATA
glaium_sdk-0.1.2.dist-info/WHEEL
glaium_sdk-0.1.2.dist-info/top_level.txt
glaium_sdk-0.1.2.dist-info/RECORD
