Metadata-Version: 2.2
Name: glaium_sdk
Version: 0.1.2
Summary: Glaium SDK in Python for managing your Systems and Optimization
Author-email: Glaium Labs <labs@glaium.io>
Project-URL: Homepage, https://glaium.io/
Keywords: Glaium,AI_System,Optimization
Requires-Python: >=3.9
Requires-Dist: requests>=2.25.0
